dash_insta_stories/DashInstaStories.py
dash_insta_stories/__init__.py
dash_insta_stories/_imports_.py
dash_insta_stories/dash_insta_stories.min.js
dash_insta_stories/dash_insta_stories.min.js.map
dash_insta_stories/metadata.json
dash_insta_stories/package-info.json
dash_insta_stories-0.0.1.dist-info/LICENSE
dash_insta_stories-0.0.1.dist-info/METADATA
dash_insta_stories-0.0.1.dist-info/WHEEL
dash_insta_stories-0.0.1.dist-info/top_level.txt
dash_insta_stories-0.0.1.dist-info/RECORD
