Metadata-Version: 2.1
Name: dash_insta_stories
Version: 0.0.1
Summary: react insta stories for dash
Author: pip install python <pipinstallpython@gmail.com>
License: MIT
Classifier: Framework :: Dash
License-File: LICENSE
